geomentions/__init__.py
geomentions/geomentions.py
geomentions/data/city_index.json.gz
geomentions/data/country_index.json.gz
geomentions-0.0.1.dist-info/LICENSE
geomentions-0.0.1.dist-info/METADATA
geomentions-0.0.1.dist-info/WHEEL
geomentions-0.0.1.dist-info/top_level.txt
geomentions-0.0.1.dist-info/RECORD
