Metadata-Version: 2.2
Name: geomentions
Version: 0.0.1
Summary: A mini Python package for geotagging text and retrieving location info.
Author-email: Malte Genschow <sense-mitten.4z@icloud.com>
License: MIT License
Project-URL: Source Code, https://github.com/MGenschow/geomentions
Project-URL: Issue Tracker, https://github.com/MGenschow/geomentions/issues
Keywords: geotagging,NLP,text processing,cities,countries,geotext
Classifier: Programming Language :: Python :: 3
Classifier: Programming Language :: Python :: 3.7
Classifier: Programming Language :: Python :: 3.8
Classifier: Programming Language :: Python :: 3.9
Classifier: Programming Language :: Python :: 3.10
Classifier: Programming Language :: Python :: 3.11
Classifier: License :: OSI Approved :: MIT License
Classifier: Operating System :: OS Independent
Requires-Python: >=3.7
License-File: LICENSE
Requires-Dist: regex
